AnalysisWeb/__init__.py
AnalysisWeb/app.py
AnalysisWeb/static/higgs_pot.jpg
AnalysisWeb/static/results_data.csv
AnalysisWeb/static/style.css
AnalysisWeb/templates/index.html
analysisweb-0.0.3.dist-info/METADATA
analysisweb-0.0.3.dist-info/WHEEL
analysisweb-0.0.3.dist-info/licenses/LICENSE
analysisweb-0.0.3.dist-info/RECORD
