Metadata-Version: 2.4
Name: AnalysisWeb
Version: 0.0.3
Summary: AnalysisWeb
Project-URL: Homepage, https://github.com/Ragansu/webapp_project
Project-URL: Issues, https://github.com/Ragansu/webapp_project/issues
Author-email: Ragansu Chakkappai <ragansu.chakkappai@universite-paris-saclay.fr>
License-File: LICENSE
Classifier: License :: OSI Approved :: MIT License
Classifier: Operating System :: OS Independent
Classifier: Programming Language :: Python :: 3
Requires-Python: >=3.9
Requires-Dist: flask>=3.0.0
Requires-Dist: numpy>=1.26.4
Requires-Dist: pandas>=2.2.2
Requires-Dist: requests>=2.31.0
